{
    "versionLabel": "1.0.0",
    "uuid": "33402e38-fd4e-45eb-86b8-1c88290fc732",
    "appKeys": {
        "dummy": 0
    },
    "longName": "SmartStatus",
    "versionCode": 1,
    "capabilities": [
        ""
    ],
    "shortName": "SmartStatus",
    "companyName": "Northpole Dev",
    "watchapp": {
        "watchface": false
    },
    "resources": {
        "media": [
            {
                "type": "png",
                "name": "IMAGE_CONNECT",
                "file": "images/connect_large.png"
            },
            {
                "characterRegex": "[:0-9]",
                "type": "font",
                "name": "FONT_ROBOTO_BOLD_SUBSET_49",
                "file": "fonts/Roboto-Bold.ttf"
            },
            {
                "type": "font",
                "name": "FONT_ROBOTO_CONDENSED_21",
                "file": "fonts/Roboto-Condensed.ttf"
            },
            {
                "type": "png",
                "name": "IMAGE_BATTERY_PEBBLE",
                "file": "images/battery_pebble.png"
            },
            {
                "type": "png",
                "name": "IMAGE_BATTERY_PHONE",
                "file": "images/battery_phone.png"
            },
            {
                "type": "png",
                "name": "IMAGE_DISCONNECT",
                "file": "images/disconnect_large.png"
            },
            {
                "type": "png",
                "name": "IMAGE_BACKGROUND",
                "file": "images/background.png"
            }
        ]
    }
}
